mccn/__init__.py
mccn/__version__.py
mccn/_types.py
mccn/client.py
mccn/config.py
mccn/drawer.py
mccn/extent.py
mccn/legend.py
mccn/loader/__init__.py
mccn/loader/base.py
mccn/loader/point/__init__.py
mccn/loader/point/config.py
mccn/loader/point/loader.py
mccn/loader/raster/__init__.py
mccn/loader/raster/config.py
mccn/loader/raster/loader.py
mccn/loader/utils.py
mccn/loader/vector/__init__.py
mccn/loader/vector/config.py
mccn/loader/vector/loader.py
mccn/parser.py
mccn_engine-0.1.11.dist-info/METADATA
mccn_engine-0.1.11.dist-info/WHEEL
mccn_engine-0.1.11.dist-info/entry_points.txt
mccn_engine-0.1.11.dist-info/licenses/LICENSE
mccn_engine-0.1.11.dist-info/RECORD
