Metadata-Version: 2.1
Name: mccn-engine
Version: 0.1.11
Summary: mccn engine
Author-Email: Joseph <joseph.sclauzero@adelaide.edu.au>
License: MIT
Requires-Python: >=3.11
Requires-Dist: odc-stac>=0.3.10
Requires-Dist: pystac-generator>=0.3.31
Requires-Dist: matplotlib>=3.10.1
Requires-Dist: pystac-client>=0.8.6
Requires-Dist: dask==2024.10.0
Requires-Dist: scipy>=1.15.2
Requires-Dist: duckdb>=1.2.2
